hdhrhttpapi/__init__.py
hdhrhttpapi-0.0.1.dist-info/LICENSE
hdhrhttpapi-0.0.1.dist-info/METADATA
hdhrhttpapi-0.0.1.dist-info/WHEEL
hdhrhttpapi-0.0.1.dist-info/top_level.txt
hdhrhttpapi-0.0.1.dist-info/RECORD
