Metadata-Version: 2.1
Name: hdhrhttpapi
Version: 0.0.1
Summary: HDHomeRun HTTP API interface library for Python 3.
Home-page: https://github.com/homected/hdhrhttpapi
Author: Jose Luis Galindo
Author-email: support@homected.com
License: UNKNOWN
Keywords: tv television tuner tvtuner hdhomerun
Platform: UNKNOWN
Classifier: Programming Language :: Python :: 3
Classifier: License :: OSI Approved :: MIT License
Classifier: Operating System :: OS Independent
Classifier: Natural Language :: English
Classifier: Topic :: Software Development :: Libraries :: Python Modules
Classifier: Topic :: Multimedia :: Video :: Capture
Requires-Python: >=3.8
